Metadata-Version: 2.1
Name: ShortReport
Version: 0.0.6
Summary: It generates the Report of the dataset
Home-page: UNKNOWN
Author: Chiransh Singh Mehra , Raghav Aggarwal
Author-email: singhchiransh4@gmail.com , raghavaggarwal200004@gmail.com
License: MIT
Keywords: report,python,data-analysis,jupyter,ShortReport
Platform: UNKNOWN
Classifier: Development Status :: 5 - Production/Stable
Classifier: Intended Audience :: Developers
Classifier: Intended Audience :: Science/Research
Classifier: Intended Audience :: Education
Classifier: Operating System :: Microsoft :: Windows :: Windows 10
Classifier: License :: OSI Approved :: MIT License
Classifier: Programming Language :: Python :: 3
License-File: LICENCE.txt
